{
  "num": "0221",
  "name": {
    "en": "Nendoroid Ai Nanasaki (ねんどろいど ななさきあい)",
    "ja": "ねんどろいど 七咲逢 (ねんどろいど ななさきあい)",
    "ko": "나나사키 아이"
  },
  "series": {
    "en": "Amagami SS",
    "ja": "アマガミSS",
    "ko": "아마가미 SS",
    "code": "amagami-ss"
  },
  "category": "regular",
  "manufacturer": "Good Smile Company",
  "sculptor": null,
  "cooperation": null,
  "release_date": [
    {
      "date": "2012-05",
      "status": "released"
    }
  ],
  "preorder": null,
  "price_jpy": 3667,
  "gsc_product_num": 3430,
  "gsc_product_url": null,
  "image": {
    "primary": "https://images.goodsmile.info/cgm/images/product/20120112/3430/16817/large/72d5a1b43e842cf702f0f08821cbe289.jpg",
    "gallery": []
  },
  "character_gender": "F",
  "tags": [],
  "variant_group_id": null,
  "variant_label": null,
  "accessories": [],
  "retailers": [],
  "source": {
    "imported_from": "NendoroidDB",
    "imported_at": "2026-05-15T14:15:03.145Z",
    "updated_at": "2026-05-15T14:15:10.423Z"
  },
  "_source_path": "Nendoroid/0200-0299/221.json"
}
