{
  "num": "0831",
  "name": {
    "en": "Nendoroid Hatsune Miku: 10th Anniversary Ver.",
    "ja": "ねんどろいど 初音ミク 10th Anniversary Ver. (ねんどろいど はつねみく 10th あにばーさりー Ver.)",
    "ko": "하츠네 미쿠 10th Anniversary Ver."
  },
  "series": {
    "en": "Character Vocal Series 01: Hatsune Miku",
    "ja": "キャラクター・ボーカル・シリーズ01 初音ミク",
    "ko": "하츠네미쿠",
    "code": "character-vocal-series-01-hatsune-miku"
  },
  "category": "regular",
  "manufacturer": "Good Smile Company",
  "sculptor": null,
  "cooperation": null,
  "release_date": [
    {
      "date": "2018-01",
      "status": "released"
    }
  ],
  "preorder": null,
  "price_jpy": 4584,
  "gsc_product_num": 6680,
  "gsc_product_url": null,
  "image": {
    "primary": "https://images.goodsmile.info/cgm/images/product/20170825/6680/47244/large/a9a9509e00acbec2ea2e7bf654af66ec.jpg",
    "gallery": []
  },
  "character_gender": "F",
  "tags": [],
  "variant_group_id": null,
  "variant_label": null,
  "accessories": [],
  "retailers": [],
  "source": {
    "imported_from": "NendoroidDB",
    "imported_at": "2026-05-15T14:15:03.366Z",
    "updated_at": "2026-05-15T14:15:10.577Z"
  },
  "_source_path": "Nendoroid/0800-0899/831.json"
}
