{
  "num": "2133",
  "name": {
    "en": "Nendoroid Yu Ishigami",
    "ja": "ねんどろいど 石上優 (ねんどろいど いしがみゆう)",
    "ko": "이시가미 유우"
  },
  "series": {
    "en": "Kaguya-sama: Love is War - The First Kiss That Never Ends",
    "ja": "かぐや様は告らせたい-ファーストキッスは終わらない-",
    "ko": "카구야 님은 고백받고 싶어",
    "code": "kaguya-sama-love-is-war-the-first-kiss-that-never-ends"
  },
  "category": "regular",
  "manufacturer": "Good Smile Company",
  "sculptor": null,
  "cooperation": null,
  "release_date": [
    {
      "date": "2023-11",
      "status": "released"
    }
  ],
  "preorder": null,
  "price_jpy": 6900,
  "gsc_product_num": 14301,
  "gsc_product_url": null,
  "image": {
    "primary": "https://images.goodsmile.info/cgm/images/product/20230421/14301/114637/large/273f0f72546919908c3bbf25344bcd77.jpg",
    "gallery": []
  },
  "character_gender": "M",
  "tags": [],
  "variant_group_id": null,
  "variant_label": null,
  "accessories": [],
  "retailers": [],
  "source": {
    "imported_from": "NendoroidDB",
    "imported_at": "2026-05-15T14:15:03.735Z",
    "updated_at": "2026-05-15T14:15:10.890Z"
  },
  "_source_path": "Nendoroid/2100-2199/2133.json"
}
