{
  "num": "0350",
  "name": {
    "en": "Nendoroid Ranka Lee (ねんどろいど らんか・りー)",
    "ja": "ねんどろいど ランカ・リー (ねんどろいど らんか・りー)",
    "ko": "란카 리"
  },
  "series": {
    "en": "Macross Frontier",
    "ja": "マクロスF（フロンティア）",
    "ko": "마크로스 프런티어",
    "code": "macross-frontier"
  },
  "category": "regular",
  "manufacturer": "Good Smile Company",
  "sculptor": null,
  "cooperation": null,
  "release_date": [
    {
      "date": "2013-11",
      "status": "released"
    }
  ],
  "preorder": null,
  "price_jpy": 3667,
  "gsc_product_num": 3989,
  "gsc_product_url": null,
  "image": {
    "primary": "https://images.goodsmile.info/cgm/images/product/20130712/3989/25091/large/804fa8590059967da88348455f40a9a3.jpg",
    "gallery": []
  },
  "character_gender": "F",
  "tags": [],
  "variant_group_id": null,
  "variant_label": null,
  "accessories": [],
  "retailers": [],
  "source": {
    "imported_from": "NendoroidDB",
    "imported_at": "2026-05-15T14:15:03.191Z",
    "updated_at": "2026-05-15T14:15:10.453Z"
  },
  "_source_path": "Nendoroid/0300-0399/350.json"
}
