{
  "num": "0471",
  "name": {
    "en": "Nendoroid Teru Miyanaga (ねんどろいど みやながてる)",
    "ja": "ねんどろいど 宮永照 (ねんどろいど みやながてる)",
    "ko": "미야나가 테루"
  },
  "series": {
    "en": "Saki Achiga-hen",
    "ja": "咲-Saki- 阿知賀編",
    "ko": "사키",
    "code": "saki-achiga-hen"
  },
  "category": "regular",
  "manufacturer": "Good Smile Company",
  "sculptor": null,
  "cooperation": null,
  "release_date": [
    {
      "date": "2015-03",
      "status": "released"
    }
  ],
  "preorder": null,
  "price_jpy": 0,
  "gsc_product_num": 4758,
  "gsc_product_url": null,
  "image": {
    "primary": "https://images.goodsmile.info/cgm/images/product/20141202/4758/31589/large/6d84125efb4751960c10a6eb9f306a82.jpg",
    "gallery": []
  },
  "character_gender": "F",
  "tags": [],
  "variant_group_id": null,
  "variant_label": null,
  "accessories": [],
  "retailers": [],
  "source": {
    "imported_from": "NendoroidDB",
    "imported_at": "2026-05-15T14:15:03.248Z",
    "updated_at": "2026-05-15T14:15:10.479Z"
  },
  "_source_path": "Nendoroid/0400-0499/471.json"
}
