{
  "num": "1144",
  "name": {
    "en": "Nendoroid Hyakkimaru",
    "ja": "ねんどろいど 百鬼丸 (ねんどろいど ひゃっきまる)",
    "ko": "햐키마루"
  },
  "series": {
    "en": "Dororo",
    "ja": "どろろ",
    "ko": "도로로",
    "code": "dororo"
  },
  "category": "regular",
  "manufacturer": "Good Smile Company",
  "sculptor": null,
  "cooperation": null,
  "release_date": [
    {
      "date": "2020-01",
      "status": "released"
    }
  ],
  "preorder": null,
  "price_jpy": 4800,
  "gsc_product_num": 8435,
  "gsc_product_url": null,
  "image": {
    "primary": "https://images.goodsmile.info/cgm/images/product/20190614/8435/61018/large/45459295d7df43a5eb9f7aed857fe0e1.jpg",
    "gallery": []
  },
  "character_gender": "M",
  "tags": [],
  "variant_group_id": null,
  "variant_label": null,
  "accessories": [],
  "retailers": [],
  "source": {
    "imported_from": "NendoroidDB",
    "imported_at": "2026-05-15T14:15:03.454Z",
    "updated_at": "2026-05-15T14:15:10.659Z"
  },
  "_source_path": "Nendoroid/1100-1199/1144.json"
}
