{
  "num": "1359",
  "name": {
    "en": "Nendoroid Nikki",
    "ja": "ねんどろいど ニキ (ねんどろいど にき)",
    "ko": "니키"
  },
  "series": {
    "en": "Shining Nikki",
    "ja": "シャイニングニキ（閃耀暖暖）",
    "ko": "샤이닝니키",
    "code": "shining-nikki"
  },
  "category": "regular",
  "manufacturer": "Good Smile Company",
  "sculptor": null,
  "cooperation": null,
  "release_date": [
    {
      "date": "2021-01",
      "status": "released"
    }
  ],
  "preorder": null,
  "price_jpy": 5000,
  "gsc_product_num": 9843,
  "gsc_product_url": null,
  "image": {
    "primary": "https://images.goodsmile.info/cgm/images/product/20200729/9843/72627/large/7404c9062e79cfd4afee8110f632f125.jpg",
    "gallery": []
  },
  "character_gender": "F",
  "tags": [],
  "variant_group_id": null,
  "variant_label": null,
  "accessories": [],
  "retailers": [],
  "source": {
    "imported_from": "NendoroidDB",
    "imported_at": "2026-05-15T14:15:03.517Z",
    "updated_at": "2026-05-15T14:15:10.722Z"
  },
  "_source_path": "Nendoroid/1300-1399/1359.json"
}
