{
  "num": "1439",
  "name": {
    "en": "Nendoroid Hatsune Miku: Kigurumi Agumon Ver.",
    "ja": "ねんどろいど 初音ミク きぐるみアグモンVer. (ねんどろいど はつねみく きぐるみあぐもんVer.)",
    "ko": "하츠네 미쿠 아구몬 Ver."
  },
  "series": {
    "en": "Character Vocal Series 01: Hatsune Miku/Digimon Adventure",
    "ja": "キャラクター・ボーカル・シリーズ01 初音ミク／デジモンアドベンチャー",
    "ko": "보컬로이드(VOCALOID)",
    "code": "character-vocal-series-01-hatsune-miku-digimon-adventure"
  },
  "category": "regular",
  "manufacturer": "Good Smile Company",
  "sculptor": null,
  "cooperation": null,
  "release_date": [
    {
      "date": "2021-05",
      "status": "released"
    }
  ],
  "preorder": null,
  "price_jpy": 5500,
  "gsc_product_num": 9918,
  "gsc_product_url": null,
  "image": {
    "primary": "https://images.goodsmile.info/cgm/images/product/20200812/9918/73546/large/3d4bcee4d67dd0e04b5b833e2159583d.jpg",
    "gallery": []
  },
  "character_gender": "F",
  "tags": [],
  "variant_group_id": null,
  "variant_label": null,
  "accessories": [],
  "retailers": [],
  "source": {
    "imported_from": "NendoroidDB",
    "imported_at": "2026-05-15T14:15:03.540Z",
    "updated_at": "2026-05-15T14:15:10.742Z"
  },
  "_source_path": "Nendoroid/1400-1499/1439.json"
}
