{
  "num": "1778",
  "name": {
    "en": "Nendoroid Sakura Kagamihara",
    "ja": "ねんどろいど 各務原桜 (ねんどろいど かがみはらさくら)",
    "ko": "카가미하라 사쿠라"
  },
  "series": {
    "en": "Laid-Back Camp",
    "ja": "ゆるキャン△",
    "ko": "유루캠△",
    "code": "laid-back-camp"
  },
  "category": "regular",
  "manufacturer": "Good Smile Company",
  "sculptor": null,
  "cooperation": null,
  "release_date": [
    {
      "date": "2022-09",
      "status": "released"
    }
  ],
  "preorder": null,
  "price_jpy": 6600,
  "gsc_product_num": 12077,
  "gsc_product_url": null,
  "image": {
    "primary": "https://images.goodsmile.info/cgm/images/product/20211202/12077/92759/large/a5d9175a7908c1178a45724f7f470b96.jpg",
    "gallery": []
  },
  "character_gender": "F",
  "tags": [],
  "variant_group_id": null,
  "variant_label": null,
  "accessories": [],
  "retailers": [],
  "source": {
    "imported_from": "NendoroidDB",
    "imported_at": "2026-05-15T14:15:03.636Z",
    "updated_at": "2026-05-15T14:15:10.813Z"
  },
  "_source_path": "Nendoroid/1700-1799/1778.json"
}
