{
  "num": "1803",
  "name": {
    "en": "Nendoroid SUGA",
    "ja": "ねんどろいど SUGA",
    "ko": "슈가"
  },
  "series": {
    "en": "TinyTAN",
    "ja": "TinyTAN",
    "ko": "방탄소년단",
    "code": "tinytan"
  },
  "category": "regular",
  "manufacturer": "Good Smile Company",
  "sculptor": null,
  "cooperation": null,
  "release_date": [
    {
      "date": "2022-09",
      "status": "released"
    }
  ],
  "preorder": null,
  "price_jpy": 5000,
  "gsc_product_num": 12184,
  "gsc_product_url": null,
  "image": {
    "primary": "https://images.goodsmile.info/cgm/images/product/20211227/12184/93839/large/a8404176e38782ce320012051f8aed35.jpg",
    "gallery": []
  },
  "character_gender": "M",
  "tags": [],
  "variant_group_id": null,
  "variant_label": null,
  "accessories": [],
  "retailers": [],
  "source": {
    "imported_from": "NendoroidDB",
    "imported_at": "2026-05-15T14:15:03.642Z",
    "updated_at": "2026-05-15T14:15:10.819Z"
  },
  "_source_path": "Nendoroid/1800-1899/1803.json"
}
