{
  "num": "1931",
  "name": {
    "en": "Nendoroid Vivy",
    "ja": "ねんどろいど ヴィヴィ (ねんどろいど ゔぃゔぃ)",
    "ko": "비비"
  },
  "series": {
    "en": "Vivy -Fluorite Eye's Song-",
    "ja": "Vivy -Fluorite Eye's Song-",
    "ko": "Vivy -Fluorite Eye’s Song-",
    "code": "vivy-fluorite-eye-s-song"
  },
  "category": "regular",
  "manufacturer": "Good Smile Company",
  "sculptor": null,
  "cooperation": null,
  "release_date": [
    {
      "date": "2023-01",
      "status": "released"
    }
  ],
  "preorder": null,
  "price_jpy": 7400,
  "gsc_product_num": 13076,
  "gsc_product_url": null,
  "image": {
    "primary": "https://images.goodsmile.info/cgm/images/product/20220804/13076/102527/large/e3cd9046fe47b8b3cf8b420592f133c7.jpg",
    "gallery": []
  },
  "character_gender": "F",
  "tags": [],
  "variant_group_id": null,
  "variant_label": null,
  "accessories": [],
  "retailers": [],
  "source": {
    "imported_from": "NendoroidDB",
    "imported_at": "2026-05-15T14:15:03.677Z",
    "updated_at": "2026-05-15T14:15:10.847Z"
  },
  "_source_path": "Nendoroid/1900-1999/1931.json"
}
