{
  "num": "1976",
  "name": {
    "en": "Nendoroid Persicaria",
    "ja": "ねんどろいど ペルシカ (ねんどろいど ぺるしか)",
    "ko": "페르시카리아"
  },
  "series": {
    "en": "NeuralCloud",
    "ja": "ニューラルクラウド",
    "ko": "뉴럴 클라우드",
    "code": "neuralcloud"
  },
  "category": "regular",
  "manufacturer": "Good Smile Company",
  "sculptor": null,
  "cooperation": null,
  "release_date": [
    {
      "date": "2023-04",
      "status": "released"
    }
  ],
  "preorder": null,
  "price_jpy": 8600,
  "gsc_product_num": 13355,
  "gsc_product_url": null,
  "image": {
    "primary": "https://images.goodsmile.info/cgm/images/product/20221003/13355/105390/large/4d4760924a48db2a9cb38b36d139466d.jpg",
    "gallery": []
  },
  "character_gender": "F",
  "tags": [],
  "variant_group_id": null,
  "variant_label": null,
  "accessories": [],
  "retailers": [],
  "source": {
    "imported_from": "NendoroidDB",
    "imported_at": "2026-05-15T14:15:03.690Z",
    "updated_at": "2026-05-15T14:15:10.855Z"
  },
  "_source_path": "Nendoroid/1900-1999/1976.json"
}
