{
  "num": "2105",
  "name": {
    "en": "Nendoroid Kyoya Ootori",
    "ja": "ねんどろいど 鳳鏡夜 (ねんどろいど おおとりきょうや)",
    "ko": "오오토리 쿄우야"
  },
  "series": {
    "en": "Ouran High School Host Club",
    "ja": "桜蘭高校ホスト部",
    "ko": "오란고교 호스트부",
    "code": "ouran-high-school-host-club"
  },
  "category": "regular",
  "manufacturer": "Good Smile Company",
  "sculptor": null,
  "cooperation": null,
  "release_date": [
    {
      "date": "2023-09",
      "status": "released"
    }
  ],
  "preorder": null,
  "price_jpy": 6500,
  "gsc_product_num": 14274,
  "gsc_product_url": null,
  "image": {
    "primary": "https://images.goodsmile.info/cgm/images/product/20230417/14274/114429/large/dbe23739e38b2a3461c9c37e25f6fcb6.jpg",
    "gallery": []
  },
  "character_gender": "M",
  "tags": [],
  "variant_group_id": null,
  "variant_label": null,
  "accessories": [],
  "retailers": [],
  "source": {
    "imported_from": "NendoroidDB",
    "imported_at": "2026-05-15T14:15:03.727Z",
    "updated_at": "2026-05-15T14:15:10.883Z"
  },
  "_source_path": "Nendoroid/2100-2199/2105.json"
}
